climate_ref_ilamb/__init__.py
climate_ref_ilamb/datasets.py
climate_ref_ilamb/py.typed
climate_ref_ilamb/standard.py
climate_ref_ilamb/configure/ilamb.yaml
climate_ref_ilamb/configure/iomb.yaml
climate_ref_ilamb/dataset_registry/ilamb.txt
climate_ref_ilamb/dataset_registry/iomb.txt
climate_ref_ilamb/dataset_registry/test.txt
climate_ref_ilamb-0.8.1.dist-info/METADATA
climate_ref_ilamb-0.8.1.dist-info/WHEEL
climate_ref_ilamb-0.8.1.dist-info/entry_points.txt
climate_ref_ilamb-0.8.1.dist-info/licenses/LICENCE
climate_ref_ilamb-0.8.1.dist-info/licenses/NOTICE
climate_ref_ilamb-0.8.1.dist-info/RECORD
