Metadata-Version: 2.4
Name: climate-ref-ilamb
Version: 0.8.1
Summary: ILAMB diagnostic provider for the Rapid Evaluation Framework
Author-email: Nathan Collier <nathaniel.collier@gmail.com>, Jared Lewis <jared.lewis@climate-resource.com>
License-Expression: Apache-2.0
License-File: LICENCE
License-File: NOTICE
Classifier: Development Status :: 3 - Alpha
Classifier: Intended Audience :: Developers
Classifier: Intended Audience :: Science/Research
Classifier: License :: OSI Approved :: Apache Software License
Classifier: Operating System :: OS Independent
Classifier: Programming Language :: Python
Classifier: Programming Language :: Python :: 3
Classifier: Programming Language :: Python :: 3.11
Classifier: Programming Language :: Python :: 3.12
Classifier: Programming Language :: Python :: 3.13
Classifier: Topic :: Scientific/Engineering
Requires-Python: >=3.11
Requires-Dist: climate-ref-core
Requires-Dist: ilamb3>=2025.9.9
Requires-Dist: scipy<1.16
